{
  "title": "Whole Earth Review, Summer 1992",
  "identifier": "wholeearthreview00unse_30",
  "year": 1992,
  "season": "Summer",
  "collection": "Whole Earth Review",
  "collection_zh": "Whole Earth Review",
  "pages": 149,
  "url": "https://wholeearth.info/p/whole-earth-review-summer-1992",
  "archive_url": "https://archive.org/details/wholeearthreview00unse_30",
  "pdf_url": "https://archive.org/download/wholeearthreview00unse_30/wholeearthreview00unse_30.pdf",
  "cover_url": "https://archive.org/download/wholeearthreview00unse_30/page/cover_w500.jpg",
  "ocr_path": "work/wholeearth/ocr/wholeearthreview00unse_30_djvu.txt",
  "ocr_chars": 650105,
  "significant_line_count": 17098,
  "theme_counts": {
    "software_computing": 143,
    "tools_craft": 149,
    "ecology_place": 361,
    "learning_media": 411,
    "community_politics": 704
  },
  "top_themes": [
    "community_politics",
    "learning_media",
    "ecology_place"
  ],
  "page_markers": [
    {
      "line": 482,
      "page": 4,
      "title": "WHOLE EARTH REVIEW SUMMER 1992",
      "image_url": "https://archive.org/download/wholeearthreview00unse_30/page/n5_w500.jpg"
    },
    {
      "line": 542,
      "page": 27,
      "title": "GATE5 ROAD _-- SAUSALITO, CA 94965 5",
      "image_url": "https://archive.org/download/wholeearthreview00unse_30/page/n28_w500.jpg"
    },
    {
      "line": 579,
      "page": 6,
      "title": "WHOLE EARTH REVIEW SUMMER 1992",
      "image_url": "https://archive.org/download/wholeearthreview00unse_30/page/n7_w500.jpg"
    },
    {
      "line": 2854,
      "page": 20,
      "title": "WHOLE EARTH REVIEW SUMMER 1992",
      "image_url": "https://archive.org/download/wholeearthreview00unse_30/page/n21_w500.jpg"
    },
    {
      "line": 3090,
      "page": 22,
      "title": "WHOLE EARTH REVIEW SUMMER 1992",
      "image_url": "https://archive.org/download/wholeearthreview00unse_30/page/n23_w500.jpg"
    },
    {
      "line": 3430,
      "page": 24,
      "title": "WHOLE EARTH REVIEW SUMMER 1992",
      "image_url": "https://archive.org/download/wholeearthreview00unse_30/page/n25_w500.jpg"
    },
    {
      "line": 3877,
      "page": 26,
      "title": "WHOLE EARTH REVIEW",
      "image_url": "https://archive.org/download/wholeearthreview00unse_30/page/n27_w500.jpg"
    },
    {
      "line": 4119,
      "page": 28,
      "title": "WHOLE EARTH REVIEW SUMMER 1992",
      "image_url": "https://archive.org/download/wholeearthreview00unse_30/page/n29_w500.jpg"
    },
    {
      "line": 4374,
      "page": 30,
      "title": "WHOLE EARTH REVIEW SUMMER 1992",
      "image_url": "https://archive.org/download/wholeearthreview00unse_30/page/n31_w500.jpg"
    },
    {
      "line": 5261,
      "page": 34,
      "title": "WHOLE EARTH REVIEW SUMMER 1992",
      "image_url": "https://archive.org/download/wholeearthreview00unse_30/page/n35_w500.jpg"
    },
    {
      "line": 5541,
      "page": 36,
      "title": "WHOLE EARTH REVIEW SUMMER 1992",
      "image_url": "https://archive.org/download/wholeearthreview00unse_30/page/n37_w500.jpg"
    },
    {
      "line": 5918,
      "page": 38,
      "title": "WHOLE EARTH REVIEW SUMMER 1992",
      "image_url": "https://archive.org/download/wholeearthreview00unse_30/page/n39_w500.jpg"
    },
    {
      "line": 6152,
      "page": 40,
      "title": "WHOLE EARTH REVIEW SUMMER 1992",
      "image_url": "https://archive.org/download/wholeearthreview00unse_30/page/n41_w500.jpg"
    },
    {
      "line": 6426,
      "page": 42,
      "title": "WHOLE EARTH REVIEW SUMMER 1992",
      "image_url": "https://archive.org/download/wholeearthreview00unse_30/page/n43_w500.jpg"
    },
    {
      "line": 6700,
      "page": 44,
      "title": "WHOLE EARTH REVIEW SUMMER 1992",
      "image_url": "https://archive.org/download/wholeearthreview00unse_30/page/n45_w500.jpg"
    },
    {
      "line": 6889,
      "page": 46,
      "title": "WHOLE EARTH REVIEW SUMMER 1992",
      "image_url": "https://archive.org/download/wholeearthreview00unse_30/page/n47_w500.jpg"
    },
    {
      "line": 7228,
      "page": 48,
      "title": "WHOLE EARTH REVIEW SUMMER 1992",
      "image_url": "https://archive.org/download/wholeearthreview00unse_30/page/n49_w500.jpg"
    },
    {
      "line": 7513,
      "page": 50,
      "title": "WHOLE EARTH REVIEW SUMMER 1992",
      "image_url": "https://archive.org/download/wholeearthreview00unse_30/page/n51_w500.jpg"
    },
    {
      "line": 7985,
      "page": 54,
      "title": "WHOLE EARTH REVIEW SUMMER 1992",
      "image_url": "https://archive.org/download/wholeearthreview00unse_30/page/n55_w500.jpg"
    },
    {
      "line": 8230,
      "page": 56,
      "title": "WHOLE EARTH REVIEW SUMMER 1992",
      "image_url": "https://archive.org/download/wholeearthreview00unse_30/page/n57_w500.jpg"
    },
    {
      "line": 8575,
      "page": 58,
      "title": "WHOLE EARTH REVIEW SUMMER 1992",
      "image_url": "https://archive.org/download/wholeearthreview00unse_30/page/n59_w500.jpg"
    },
    {
      "line": 8943,
      "page": 60,
      "title": "WHOLE EARTH REVIEW SUMMER 1992",
      "image_url": "https://archive.org/download/wholeearthreview00unse_30/page/n61_w500.jpg"
    },
    {
      "line": 9174,
      "page": 62,
      "title": "WHOLE EARTH REVIEW SUMMER 1992",
      "image_url": "https://archive.org/download/wholeearthreview00unse_30/page/n63_w500.jpg"
    },
    {
      "line": 9459,
      "page": 64,
      "title": "WHOLE EARTH REVIEW SUMMER 1992",
      "image_url": "https://archive.org/download/wholeearthreview00unse_30/page/n65_w500.jpg"
    }
  ],
  "candidate_headings": [
    {
      "line": 482,
      "text": "4 WHOLE EARTH REVIEW SUMMER 1992",
      "score": 10
    },
    {
      "line": 579,
      "text": "6 WHOLE EARTH REVIEW SUMMER 1992",
      "score": 10
    },
    {
      "line": 2854,
      "text": "20 WHOLE EARTH REVIEW SUMMER 1992",
      "score": 10
    },
    {
      "line": 3090,
      "text": "22 WHOLE EARTH REVIEW SUMMER 1992",
      "score": 10
    },
    {
      "line": 3430,
      "text": "24 WHOLE EARTH REVIEW SUMMER 1992",
      "score": 10
    },
    {
      "line": 3877,
      "text": "26 WHOLE EARTH REVIEW",
      "score": 10
    },
    {
      "line": 4119,
      "text": "28 WHOLE EARTH REVIEW SUMMER 1992",
      "score": 10
    },
    {
      "line": 4374,
      "text": "30 WHOLE EARTH REVIEW SUMMER 1992",
      "score": 10
    },
    {
      "line": 5261,
      "text": "34 WHOLE EARTH REVIEW SUMMER 1992",
      "score": 10
    },
    {
      "line": 5541,
      "text": "36 WHOLE EARTH REVIEW SUMMER 1992",
      "score": 10
    },
    {
      "line": 5918,
      "text": "38 WHOLE EARTH REVIEW SUMMER 1992",
      "score": 10
    },
    {
      "line": 6152,
      "text": "40 WHOLE EARTH REVIEW SUMMER 1992",
      "score": 10
    },
    {
      "line": 6426,
      "text": "42 WHOLE EARTH REVIEW SUMMER 1992",
      "score": 10
    },
    {
      "line": 6700,
      "text": "44 WHOLE EARTH REVIEW SUMMER 1992",
      "score": 10
    },
    {
      "line": 6889,
      "text": "46 WHOLE EARTH REVIEW SUMMER 1992",
      "score": 10
    },
    {
      "line": 7228,
      "text": "48 WHOLE EARTH REVIEW SUMMER 1992",
      "score": 10
    },
    {
      "line": 7513,
      "text": "50 WHOLE EARTH REVIEW SUMMER 1992",
      "score": 10
    },
    {
      "line": 7985,
      "text": "54 WHOLE EARTH REVIEW SUMMER 1992",
      "score": 10
    },
    {
      "line": 8230,
      "text": "56 WHOLE EARTH REVIEW SUMMER 1992",
      "score": 10
    },
    {
      "line": 8575,
      "text": "58 WHOLE EARTH REVIEW SUMMER 1992",
      "score": 10
    },
    {
      "line": 8943,
      "text": "60 WHOLE EARTH REVIEW SUMMER 1992",
      "score": 10
    },
    {
      "line": 9174,
      "text": "62 WHOLE EARTH REVIEW SUMMER 1992",
      "score": 10
    },
    {
      "line": 9459,
      "text": "64 WHOLE EARTH REVIEW SUMMER 1992",
      "score": 10
    },
    {
      "line": 9679,
      "text": "66 WHOLE EARTH REVIEW SUMMER 1992",
      "score": 10
    },
    {
      "line": 10000,
      "text": "68 WHOLE EARTH REVIEW SUMMER 1992",
      "score": 10
    },
    {
      "line": 10297,
      "text": "70 WHOLE EARTH REVIEW SUMMER 1992",
      "score": 10
    },
    {
      "line": 10681,
      "text": "72 WHOLE EARTH REVIEW SUMMER 1992",
      "score": 10
    },
    {
      "line": 10981,
      "text": "74 WHOLE EARTH REVIEW SUMMER 1992",
      "score": 10
    },
    {
      "line": 11431,
      "text": "76 WHOLE EARTH REVIEW SUMMER 1992",
      "score": 10
    },
    {
      "line": 11675,
      "text": "78 WHOLE EARTH REVIEW SUMMER 1992",
      "score": 10
    },
    {
      "line": 12378,
      "text": "82 WHOLE EARTH REVIEW SUMMER 1992",
      "score": 10
    },
    {
      "line": 12742,
      "text": "84 WHOLE EARTH REVIEW SUMMER 1992",
      "score": 10
    },
    {
      "line": 13052,
      "text": "86 WHOLE EARTH REVIEW SUMMER 1992",
      "score": 10
    },
    {
      "line": 13553,
      "text": "90 WHOLE EARTH REVIEW SUMMER 1992",
      "score": 10
    },
    {
      "line": 13876,
      "text": "92 WHOLE EARTH REVIEW SUMMER 1992",
      "score": 10
    },
    {
      "line": 14250,
      "text": "94 WHOLE EARTH REVIEW SUMMER 1992",
      "score": 10
    },
    {
      "line": 14490,
      "text": "96 WHOLE EARTH REVIEW SUMMER 1992",
      "score": 10
    },
    {
      "line": 14913,
      "text": "98 WHOLE EARTH REVIEW SUMMER 1992",
      "score": 10
    },
    {
      "line": 755,
      "text": "27 GATE5 ROAD SAUSALITO, CA 94965 7",
      "score": 8
    },
    {
      "line": 1302,
      "text": "27 GATE 5 ROAD",
      "score": 8
    },
    {
      "line": 1642,
      "text": "27 GATES ROAD SAUSALITO, CA 94965",
      "score": 8
    },
    {
      "line": 1963,
      "text": "27 GATE5 ROAD SAUSALITO, CA 94965",
      "score": 8
    },
    {
      "line": 2809,
      "text": "27 GATE5 ROAD -- SAUSALITO, CA 94965",
      "score": 8
    },
    {
      "line": 3064,
      "text": "27 GATE5 ROAD -- SAUSALITO, CA 94965 2 I",
      "score": 8
    },
    {
      "line": 3386,
      "text": "27 GATE5 ROAD SAUSALITO, CA 94965 23",
      "score": 8
    },
    {
      "line": 4306,
      "text": "27 GATES ROAD SAUSALITO, CA 94965 29",
      "score": 8
    },
    {
      "line": 5220,
      "text": "27 GATE5 ROAD - SAUSALITO, CA 94965 3 3",
      "score": 8
    },
    {
      "line": 5468,
      "text": "27 GATE5 ROAD SAUSALITO, CA 94965 3 5",
      "score": 8
    },
    {
      "line": 6652,
      "text": "27 GATE5 ROAD --- SAUSALITO, CA 94965 43",
      "score": 8
    },
    {
      "line": 7193,
      "text": "27 GATES ROAD SAUSALITO, CA 94965 4 7",
      "score": 8
    },
    {
      "line": 7440,
      "text": "27 GATE5 ROAD SAUSALITO, CA 94965 49",
      "score": 8
    },
    {
      "line": 8490,
      "text": "27 GATE5 ROAD -- SAUSALITO, CA 94965 5 7",
      "score": 8
    },
    {
      "line": 8886,
      "text": "27 GATE5 ROAD SAUSALITO, CA 94965 5 9",
      "score": 8
    },
    {
      "line": 9424,
      "text": "27 GATE5 ROAD SAUSALITO, CA 94965 6 3",
      "score": 8
    },
    {
      "line": 9583,
      "text": "27 GATES ROAD - SAUSALITO, CA 94965 6 5",
      "score": 8
    },
    {
      "line": 9952,
      "text": "27 GATE5 ROAD -- SAUSALITO, CA 94965 6 7",
      "score": 8
    },
    {
      "line": 10615,
      "text": "27 GATES ROAD --- SAUSALITO, CA 94965",
      "score": 8
    },
    {
      "line": 10908,
      "text": "27 GATES ROAD SAUSALITO, CA 94965 73",
      "score": 8
    },
    {
      "line": 11390,
      "text": "27 GATE5 ROAD -- SAUSALITO, CA 94965 75",
      "score": 8
    },
    {
      "line": 11992,
      "text": "27 GATES ROAD SAUSALITO, CA 94965 79",
      "score": 8
    },
    {
      "line": 13752,
      "text": "27 GATE5 ROAD -- SAUSALITO, CA 94965 9 I",
      "score": 8
    },
    {
      "line": 14206,
      "text": "27 GATE5 ROAD SAUSALITO, CA 94965 93",
      "score": 8
    },
    {
      "line": 14415,
      "text": "27 GATE5 ROAD -- SAUSALITO, CA 94965 9 5",
      "score": 8
    },
    {
      "line": 17822,
      "text": "27 GATE5 ROAD, SAUSALITO, CA 94965",
      "score": 8
    },
    {
      "line": 20699,
      "text": "27 GATE 5 ROAD - SAUSALITO, CA 94965",
      "score": 8
    },
    {
      "line": 823,
      "text": "8 . WHOLE EARTH REVIEW SUMMER 1992",
      "score": 6
    },
    {
      "line": 1179,
      "text": "I 0 WHOLE EARTH REVIEW SUMMER 1992",
      "score": 6
    },
    {
      "line": 1371,
      "text": "| 2 WHOLE EARTH REVIEW SUMMER 1992",
      "score": 6
    },
    {
      "line": 1749,
      "text": "| 4 WHOLE EARTH REVIEW SUMMER 1992",
      "score": 6
    },
    {
      "line": 2048,
      "text": "I 6 WHOLE EARTH REVIEW SUMMER 1992",
      "score": 6
    },
    {
      "line": 2487,
      "text": "i 8 ~WHOLE EARTH REVIEW SUMMER 1992",
      "score": 6
    },
    {
      "line": 4831,
      "text": "3 2 WHOLE EARTH REVIEW SUMMER 1992",
      "score": 6
    },
    {
      "line": 7803,
      "text": "5 2 WHOLE EARTH REVIEW SUMMER 1992",
      "score": 6
    },
    {
      "line": 12045,
      "text": "‘ 80 WHOLE EARTH REVIEW SUMMER 1992",
      "score": 6
    },
    {
      "line": 13327,
      "text": "88 WHOLE EARTH REVIEW © SUMMER 1992",
      "score": 6
    },
    {
      "line": 15328,
      "text": "l 00 WHOLE EARTH REVIEW SUMMER 1992",
      "score": 6
    },
    {
      "line": 15698,
      "text": "| 02 WHOLE EARTH REVIEW SUMMER 1992",
      "score": 6
    },
    {
      "line": 16180,
      "text": "i 04 WHOLE EARTH REVIEW SUMMER 1992",
      "score": 6
    },
    {
      "line": 16440,
      "text": "i 06 WHOLE EARTH REVIEW SUMMER 1992",
      "score": 6
    },
    {
      "line": 16835,
      "text": "| 08 WHOLE EARTH REVIEW SUMMER 1992",
      "score": 6
    }
  ],
  "snippets": [
    {
      "line": 11,
      "term": "tools",
      "snippet": "-Telegeography ° Sex Zines ¢ Useful Plants No. 75 um mer 1992 ACCESS TO TOOLS & IDEAS EOPLE ASK WHAT the “theme” of the next issue is going to be."
    },
    {
      "line": 32,
      "term": "tools",
      "snippet": "tion of this issue is about “Mutual Hypnosis,” one of a series of articles about research into the nature of empathy, creativ- ity, spiritual awareness - new tools forthink- _ ing about old questions about human poten- tial. But the first articles are about some- thing very different: “Vigil” and “Under"
    },
    {
      "line": 76,
      "term": "interview",
      "snippet": "WHETHER a telephone is used to seal a marriage between New York and New Delhi, to confirm a line of credit between Seattle and Singapore, or to conduct an interview between Boston and Beijing, a new geography is being created - socially, economically, and politically. But the telegeography of the 1990s does not resemble McLuhan's “global electronic village.” The village metaphor suggests that the spread of tele-"
    },
    {
      "line": 390,
      "term": "whole systems",
      "snippet": "Your Daughter Abigail Van Buren 104 Just Say Yes WHOLE SYSTEMS Richard Kadrey 47 Earth in the Balance 96 Susie Sexpert's Lesbian World * State of the World 1992 98 Herotica * Herotica 2 57 Ancient Futures = hd"
    },
    {
      "line": 421,
      "term": "learning",
      "snippet": "* Long Haul Cargo Bicycle 128 What? Music! 57. Rainforests --- Jonathan E. sryeiee an Tae LEARNING/CRAFT 17 ‘The Whole Language Catalog 102 Alaska, HO! 26 The Merle Clamp 32 Less Than Words Can Say 103 The Boundary Waters Catalog 27 Shaker Life, Work, and Art 130 Twisted Sisters 121 Passport to Freedom 37° tn The Mind's, Eye"
    },
    {
      "line": 493,
      "term": "community",
      "snippet": "“talking” to. I had never laid eyes on them. At 3:00 AM my “real” friends were asleep, so I turned to this foreign, invisible community for support. The WELL was always awake. Any difficulty is harder to bear in isolation. There is nothing to measure against, to lean against."
    },
    {
      "line": 676,
      "term": "learning",
      "snippet": "ties. We both clean the stoma. We both suction. The other parents are learning their new skills at the same time. We are awkward at first, but soon we work around our children’s"
    },
    {
      "line": 1049,
      "term": "tools",
      "snippet": "‘Once we physicians start listening to patients and respecting and sharing with them, they will give us extra tools to help in the healing process. _»In many ways, the physician is as poorly equipped to handle failure as the patient."
    },
    {
      "line": 1794,
      "term": "tools",
      "snippet": "it has helped me and my whole family - and | see it as something to add to the complement of available tools, beginning with medical treatment. Even if it could be shown that prayer had no effect on medical outcomes (which"
    },
    {
      "line": 1803,
      "term": "community",
      "snippet": "will you probably didn’t know you had. And the prayers of others can create an expanded community of concern whose love will support you ineffably but tangibly. . Turning to the more practical,"
    },
    {
      "line": 1841,
      "term": "community",
      "snippet": "lifetime’s worth of lessons about love, communication, courage, pur- posefulness, sacrifice, community, prayer, healing, darkness, fear, per- severance, and the tenuousness of this existence. I often think of this"
    },
    {
      "line": 1952,
      "term": "community",
      "snippet": "ers to the hospital for no reason. Patients, families, and staff form a de facto community, and need to act like one. That means turning to each other for information, to process complaints or misunderstandings, and to find ways"
    }
  ],
  "opening_lines": [
    {
      "line": 4,
      "text": "- Jewish and Middle Eastern Feminism"
    },
    {
      "line": 5,
      "text": "-Telegeography ° Sex Zines ¢ Useful Plants"
    },
    {
      "line": 8,
      "text": "No. 75 um mer 1992"
    },
    {
      "line": 11,
      "text": "ACCESS TO TOOLS & IDEAS"
    },
    {
      "line": 14,
      "text": "EOPLE ASK WHAT"
    },
    {
      "line": 16,
      "text": "the “theme” of the next"
    },
    {
      "line": 17,
      "text": "issue is going to be."
    },
    {
      "line": 18,
      "text": "Sometimes there is indeed"
    },
    {
      "line": 19,
      "text": "a theme, like “helping na-"
    },
    {
      "line": 20,
      "text": "ture heal” or “questioning"
    },
    {
      "line": 21,
      "text": "technology.” Most of the time,"
    },
    {
      "line": 22,
      "text": "the diversity of the articles is the"
    },
    {
      "line": 23,
      "text": "theme. The cover of an issue can"
    },
    {
      "line": 24,
      "text": "make it look like a theme issue"
    },
    {
      "line": 25,
      "text": "when it is really a mixture, an"
    },
    {
      "line": 26,
      "text": "ensemble, amosaic-acompound"
    },
    {
      "line": 27,
      "text": "lens instead of a spotlight. But it isn’t easy to come up"
    },
    {
      "line": 28,
      "text": "with a cover that simultaneously illustrates several themes,"
    },
    {
      "line": 29,
      "text": "so we almost always choose one of them. The cover illustra-"
    },
    {
      "line": 30,
      "text": "tion of this issue is about “Mutual Hypnosis,” one of a series"
    },
    {
      "line": 31,
      "text": "of articles about research into the nature of empathy, creativ-"
    },
    {
      "line": 32,
      "text": "ity, spiritual awareness - new tools forthink- _"
    },
    {
      "line": 33,
      "text": "ing about old questions about human poten-"
    },
    {
      "line": 34,
      "text": "tial. But the first articles are about some-"
    },
    {
      "line": 35,
      "text": "thing very different: “Vigil” and “Under"
    },
    {
      "line": 36,
      "text": "Siege” are about the way parents feel,"
    },
    {
      "line": 37,
      "text": "and what they do, when catastrophic"
    },
    {
      "line": 38,
      "text": "illness strikes their children."
    },
    {
      "line": 41,
      "text": "“Invisible Literature” would be"
    },
    {
      "line": 42,
      "text": "strange wherever you putit, so"
    },
    {
      "line": 43,
      "text": "it fits that awkward transi-"
    },
    {
      "line": 44,
      "text": "tion from sick kids to states"
    },
    {
      "line": 46,
      "text": "of consciousness. Jerod"
    },
    {
      "line": 47,
      "text": "Pore is anew WER author, a"
    },
    {
      "line": 48,
      "text": "scholar from the outlaw edges"
    },
    {
      "line": 49,
      "text": "of technology, with an odd"
    },
    {
      "line": 50,
      "text": "counterespionage tool of the info age."
    },
    {
      "line": 51,
      "text": "Articles and reviews related to consciousness"
    },
    {
      "line": 52,
      "text": "flow into material about ethnobotany, plant lore,"
    },
    {
      "line": 55,
      "text": "We are not sophisti-"
    }
  ]
}